{
  "version": "7",
  "dialect": "postgresql",
  "entries": [
    {
      "idx": 0,
      "version": "7",
      "when": 1769883268638,
      "tag": "0000_melted_speed_demon",
      "breakpoints": true
    },
    {
      "idx": 1,
      "version": "7",
      "when": 1770042267462,
      "tag": "0001_sweet_prowler",
      "breakpoints": true
    },
    {
      "idx": 2,
      "version": "7",
      "when": 1770216292372,
      "tag": "0002_spicy_phil_sheldon",
      "breakpoints": true
    },
    {
      "idx": 3,
      "version": "7",
      "when": 1770216370767,
      "tag": "0003_eager_power_pack",
      "breakpoints": true
    }
  ]
}